main.py
2048_py-0.1.6.dist-info/LICENSE
2048_py-0.1.6.dist-info/METADATA
2048_py-0.1.6.dist-info/WHEEL
2048_py-0.1.6.dist-info/entry_points.txt
2048_py-0.1.6.dist-info/top_level.txt
2048_py-0.1.6.dist-info/RECORD
