Metadata-Version: 2.1
Name: 2048-py
Version: 0.1.6
Summary: 2048 written in Python by the Ladue High School Computer Science Club
Home-page: https://github.com/Ta180m/2048
Author: Anthony Wang
Author-email: ta180m@gmail.com
License: UNKNOWN
Platform: UNKNOWN
Classifier: Environment :: Console
Classifier: Intended Audience :: End Users/Desktop
Classifier: Programming Language :: Python :: 3
Classifier: License :: OSI Approved :: GNU General Public License v3 (GPLv3)
Classifier: Operating System :: OS Independent
Classifier: Topic :: Games/Entertainment :: Puzzle Games
Requires-Dist: termcolor
